{"data":{"user":{"name":"Raman Kumar Rudraraju","bio":"Software Developer | Security Researcher | EV's Researcher","avatarUrl":"https://avatars.githubusercontent.com/u/30767481?v=4","location":null,"pinnedItems":{"totalCount":4,"edges":[{"node":{"name":"Dos_attack_detection_and_prevention","description":"This project contains the files for home automatin using nodemcu and iot attack programs","forkCount":0,"stargazers":{"totalCount":0},"url":"https://github.com/ramankumarrudr/Dos_attack_detection_and_prevention","id":"MDEwOlJlcG9zaXRvcnkxNzcyODI0Mzg=","diskUsage":164,"primaryLanguage":{"name":"Python","color":"#3572A5"}}},{"node":{"name":"Dynamic-Traffic-sign-Detection-System","description":"This repo consists the code and project files for a Dynamic Traffic-Sign Detection System with audio output. This solution is developed for National Level social hackathon 2019 conducted at CMRIT college bengaluru.","forkCount":0,"stargazers":{"totalCount":0},"url":"https://github.com/ramankumarrudr/Dynamic-Traffic-sign-Detection-System","id":"MDEwOlJlcG9zaXRvcnkxOTE3OTgyNTU=","diskUsage":138,"primaryLanguage":{"name":"Python","color":"#3572A5"}}},{"node":{"name":"Assignment1-busigence-technologies-","description":"Multi Image classifer Developed as assignment for busigence technologies","forkCount":0,"stargazers":{"totalCount":0},"url":"https://github.com/ramankumarrudr/Assignment1-busigence-technologies-","id":"MDEwOlJlcG9zaXRvcnkyMDI5MTY4MzQ=","diskUsage":27,"primaryLanguage":{"name":"Jupyter Notebook","color":"#DA5B0B"}}},{"node":{"name":"ImdbClone_DeltaX","description":null,"forkCount":0,"stargazers":{"totalCount":0},"url":"https://github.com/ramankumarrudr/ImdbClone_DeltaX","id":"MDEwOlJlcG9zaXRvcnkxOTk2OTk1MzQ=","diskUsage":781,"primaryLanguage":{"name":"Python","color":"#3572A5"}}}]}}}}